selfwrapper
